KEGE22/__init__.py
KEGE22-1.0.dist-info/METADATA
KEGE22-1.0.dist-info/WHEEL
KEGE22-1.0.dist-info/top_level.txt
KEGE22-1.0.dist-info/RECORD
