Metadata-Version: 2.1
Name: KEGE22
Version: 1.0
Summary: ege22
Home-page: UNKNOWN
Author: ShakeDLL
Author-email: repetskys@yandex.ru
License: UNKNOWN
Platform: UNKNOWN
Classifier: Programming Language :: Python :: 3
Classifier: License :: OSI Approved :: MIT License
Classifier: Operating System :: OS Independent
Requires-Python: >=3.6
